pushjournal/__init__.py
pushjournal/__version__.py
pushjournal/_compat.py
pushjournal/config.py
pushjournal/main.py
pushjournal/notifiers.py
pushjournal-0.2.0.dist-info/DESCRIPTION.rst
pushjournal-0.2.0.dist-info/METADATA
pushjournal-0.2.0.dist-info/RECORD
pushjournal-0.2.0.dist-info/WHEEL
pushjournal-0.2.0.dist-info/entry_points.txt
pushjournal-0.2.0.dist-info/metadata.json
pushjournal-0.2.0.dist-info/top_level.txt
