Metadata-Version: 2.0
Name: pushjournal
Version: 0.2.0
Summary: Get notified about important events via PushBullet
Home-page: UNKNOWN
Author: Roey Darwish Dror
Author-email: roey.ghost@gmail.com
License: BSD
Platform: UNKNOWN
Classifier: Programming Language :: Python :: 2.7
Classifier: Programming Language :: Python :: 3.4
Classifier: Programming Language :: Python :: 3.5
Classifier: Intended Audience :: System Administrators
Classifier: Operating System :: POSIX :: Linux
Classifier: Topic :: System :: Monitoring
Requires-Dist: PyYAML
Requires-Dist: click
Requires-Dist: logbook
Requires-Dist: netifaces
Requires-Dist: requests
